{
    "domain": "Risk Management",

    "specializations": [
        
{
  "name": "Company Secretary (CS)",

  "summary": "A Company Secretary is a corporate governance and compliance professional responsible for ensuring that a company complies with legal, regulatory, and statutory requirements while advising the board on governance matters.",

  "difficulty": "Hard",

  "goals": [
    "Ensure legal and regulatory compliance",
    "Support corporate governance",
    "Advise the board of directors",
    "Manage corporate filings and statutory obligations"
  ],

  "bestFor": [
    "People interested in corporate law and governance",
    "Detail-oriented individuals",
    "Strong communicators",
    "Those who enjoy regulatory and compliance work"
  ],

  "avoidIf": [
    "You dislike laws and regulations",
    "You prefer quantitative finance roles",
    "You dislike documentation and compliance work",
    "You want a highly creative career"
  ],

  "requiredSkills": [
    "Corporate Law",
    "Compliance Management",
    "Corporate Governance",
    "Communication",
    "Attention to Detail",
    "Documentation",
    "Regulatory Interpretation",
    "Stakeholder Management"
  ],

  "collegeImportance": [
    "Low to Moderate",
    "Professional qualification matters more than college brand",
    "Experience and practical exposure become more important over time"
  ],

  "familyAdvantage": [
    "Family-owned business",
    "Legal or compliance background",
    "Corporate network access",
    "Established professional practice"
  ],

  "qualifications": [
    "Company Secretary (CS) Qualification from ICSI",
    "Bachelor's Degree (optional but common)",
    "LLB (optional)",
    "Additional Corporate Law Certifications"
  ],

  "realityCheck": [
    "Passing CS exams requires significant effort",
    "Work is heavily compliance-oriented",
    "Attention to detail is critical",
    "Mistakes can have serious legal consequences",
    "Work can become repetitive in some organizations"
  ],

  "careerGrowth": [
    "CS Trainee",
    "Assistant Company Secretary",
    "Company Secretary",
    "Senior Company Secretary",
    "Head of Compliance",
    "Chief Compliance Officer",
    "Board Advisor"
  ],

  "salary": {
    "entry": "₹4-8 LPA",
    "mid": "₹10-25 LPA",
    "senior": "₹25 LPA - ₹1 Cr+"
  },

  "dayToDayWork": [
    "Preparing board meeting documents",
    "Managing statutory filings",
    "Ensuring regulatory compliance",
    "Advising management on legal matters",
    "Maintaining corporate records",
    "Coordinating with regulators and auditors"
  ],

  "challenges": [
    "Constant regulatory changes",
    "High compliance responsibility",
    "Strict filing deadlines",
    "Managing legal risks",
    "Maintaining accuracy in documentation"
  ],

  "roadmap": [
    "Complete 10+2",
    "Register for the CS program through ICSI",
    "Clear all examination levels",
    "Complete mandatory training",
    "Gain experience in corporate compliance and governance",
    "Progress into senior governance and compliance roles"
  ],

  "exitOpportunities": [
    "Corporate Law",
    "Compliance Management",
    "Legal Consulting",
    "Corporate Governance Advisory",
    "Risk Management",
    "Corporate Affairs",
    "Independent Practice"
  ],

  "futureOutlook": [
    "Growing regulatory requirements increase demand",
    "Corporate governance is becoming more important globally",
    "Strong demand in listed companies and large organizations",
    "Compliance and governance functions will remain essential",
    "Stable long-term career prospects"
  ],

  "recommendedResource": [
    "ICSI Study Material",
    "Companies Act, 2013",
    "SEBI Regulations",
    "Taxmann Corporate Law Publications",
    "Corporate Law Reporter"
  ]
},

{
  "name": "Risk Management",

  "summary": "Risk Management involves identifying, assessing, monitoring, and mitigating risks that could impact an organization's financial performance, operations, reputation, regulatory compliance, or strategic objectives. Risk professionals help businesses avoid major losses while supporting sustainable growth.",

  "difficulty": "Hard",

  "goals": [
    "Protect the organization from potential losses",
    "Ensure regulatory compliance",
    "Improve decision-making through risk assessment",
    "Maintain financial and operational stability",
    "Build resilient business processes"
  ],

  "bestFor": [
    "Analytical thinkers",
    "People who enjoy problem-solving",
    "Detail-oriented individuals",
    "Professionals interested in finance and regulations",
    "Individuals who prefer structured work environments"
  ],

  "avoidIf": [
    "You dislike regulations and compliance",
    "You want highly creative work",
    "You enjoy taking risks rather than managing them",
    "You prefer highly dynamic sales or client-facing careers"
  ],

  "requiredSkills": [
    "Risk Analysis",
    "Financial Analysis",
    "Statistics",
    "Excel",
    "Data Analysis",
    "Regulatory Knowledge",
    "Problem Solving",
    "Report Writing"
  ],

  "collegeImportance": [
    "Moderate",
    "Top colleges help with entry into leading banks and consulting firms",
    "Professional certifications become more important as careers progress",
    "Skills often matter more than brand after the first few years"
  ],

  "familyAdvantage": [
    "Finance industry exposure",
    "Banking connections",
    "Professional network access",
    "Mentorship from finance professionals"
  ],

  "qualifications": [
    "Bachelor's Degree (Finance, Economics, Commerce, Engineering, Mathematics)",
    "MBA Finance (optional)",
    "FRM (Financial Risk Manager)",
    "CFA (optional)",
    "Professional Risk Certifications"
  ],

  "realityCheck": [
    "Risk Management is often misunderstood as boring compliance work",
    "Good risk professionals directly influence billion-dollar decisions",
    "Mistakes become visible only when things go wrong",
    "Many successful risk managers operate behind the scenes",
    "The role becomes increasingly strategic at senior levels",
    "Work-life balance is usually better than investment banking"
  ],

  "careerGrowth": [
    "Risk Analyst",
    "Senior Risk Analyst",
    "Risk Manager",
    "Senior Risk Manager",
    "Head of Risk",
    "Chief Risk Officer (CRO)"
  ],

  "salary": {
    "entry": "₹6-12 LPA",
    "mid": "₹15-35 LPA",
    "senior": "₹40 LPA - ₹1 Cr+"
  },

  "dayToDayWork": [
    "Evaluating business risks",
    "Reviewing financial exposures",
    "Preparing risk reports",
    "Monitoring regulatory changes",
    "Stress testing scenarios",
    "Meeting business teams",
    "Developing risk frameworks",
    "Conducting audits and reviews"
  ],

  "challenges": [
    "Balancing growth and risk",
    "Regulatory complexity",
    "Unpredictable market events",
    "Communicating risks to management",
    "Handling crises when risks materialize",
    "Keeping up with changing regulations"
  ],

  "roadmap": [
    "Build strong finance and accounting fundamentals",
    "Learn statistics and data analysis",
    "Master Excel and risk modelling",
    "Study banking and financial markets",
    "Pursue FRM certification",
    "Gain experience in banking, consulting, or risk functions"
  ],

  "exitOpportunities": [
    "Compliance",
    "Internal Audit",
    "Corporate Finance",
    "Treasury",
    "Financial Consulting",
    "Banking Leadership",
    "Chief Risk Officer Track"
  ],

  "futureOutlook": [
    "Strong demand due to increasing regulations",
    "Cybersecurity and operational risks are creating new opportunities",
    "Financial institutions continue expanding risk teams",
    "AI will improve risk monitoring but not replace judgment",
    "Excellent long-term stability"
  ],

  "recommendedResource": [
    "FRM Curriculum",
    "GARP Resources",
    "Risk Management and Financial Institutions by John Hull",
    "CFA Curriculum",
    "Basel Framework Resources"
  ]
},
{
  "name": "Credit Risk Analyst",

  "summary": "Credit Risk Analysts assess the likelihood that borrowers may fail to repay loans or meet financial obligations. They analyze financial statements, credit reports, business models, industry conditions, and economic trends to help banks and financial institutions make lending decisions.",

  "difficulty": "Medium-Hard",

  "goals": [
    "Minimize loan defaults",
    "Assess borrower creditworthiness",
    "Protect the institution's capital",
    "Support profitable lending decisions",
    "Maintain portfolio quality",
    "Balance risk and return"
  ],

  "bestFor": [
    "People interested in banking and finance",
    "Analytical thinkers",
    "Individuals who enjoy financial statement analysis",
    "Risk-conscious professionals",
    "People who enjoy structured decision-making"
  ],

  "avoidIf": [
    "You dislike accounting",
    "You dislike analyzing financial statements",
    "You want highly dynamic deal-making work",
    "You dislike documentation",
    "You prefer creative careers"
  ],

  "requiredSkills": [
    "Financial Statement Analysis",
    "Accounting",
    "Credit Analysis",
    "Risk Assessment",
    "Excel",
    "Business Analysis",
    "Report Writing",
    "Industry Research"
  ],

  "collegeImportance": [
    "Moderate",
    "Good finance programs help with entry-level opportunities",
    "Professional certifications become more valuable later",
    "Skills matter more than college prestige after a few years"
  ],

  "familyAdvantage": [
    "Banking background",
    "Finance industry exposure",
    "Business family experience",
    "Professional network"
  ],

  "qualifications": [
    "B.Com, BBA, Economics, Finance, Engineering",
    "MBA Finance (optional)",
    "CFA (valuable)",
    "FRM (valuable)",
    "Credit Risk Certifications"
  ],

  "realityCheck": [
    "The job involves much more accounting than most students expect",
    "You are often responsible for saying 'no' when others want to approve a loan",
    "Mistakes can result in significant financial losses",
    "The role is less glamorous than investment banking but often more stable",
    "Senior professionals influence large lending decisions worth crores",
    "Judgment matters as much as financial models"
  ],

  "careerGrowth": [
    "Credit Analyst",
    "Senior Credit Analyst",
    "Credit Risk Manager",
    "Senior Risk Manager",
    "Head of Credit Risk",
    "Chief Risk Officer (CRO)"
  ],

  "salary": {
    "entry": "₹5-10 LPA",
    "mid": "₹12-25 LPA",
    "senior": "₹30 LPA - ₹80 LPA+"
  },

  "dayToDayWork": [
    "Analyzing financial statements",
    "Reviewing loan applications",
    "Assessing borrower repayment capacity",
    "Studying industry trends",
    "Preparing credit memos",
    "Conducting risk assessments",
    "Monitoring loan portfolios",
    "Meeting relationship managers and lending teams"
  ],

  "challenges": [
    "Incomplete borrower information",
    "Economic uncertainty",
    "Pressure from business teams to approve loans",
    "Balancing growth and risk",
    "Credit losses during downturns",
    "Making decisions with imperfect information"
  ],

  "roadmap": [
    "Learn accounting fundamentals",
    "Master financial statement analysis",
    "Understand banking and lending",
    "Develop Excel and financial modelling skills",
    "Study credit risk concepts",
    "Gain experience in banking, lending, or risk functions"
  ],

  "exitOpportunities": [
    "Corporate Banking",
    "Commercial Banking",
    "Risk Management",
    "Credit Rating Agencies",
    "Corporate Finance",
    "Private Credit",
    "Investment Analysis",
    "Chief Risk Officer Track"
  ],

  "futureOutlook": [
    "Banks will always need credit assessment professionals",
    "Private credit markets are growing rapidly",
    "AI will assist analysis but not replace judgment",
    "Strong demand in banking and NBFCs",
    "Stable long-term career path"
  ],

  "recommendedResource": [
    "The Bank Credit Analysis Handbook",
    "CFA Curriculum",
    "FRM Curriculum",
    "Moody's Credit Analysis Resources",
    "Financial Statement Analysis by Martin Fridson"
  ]
},
{
  "name": "Market Risk Analyst",

  "summary": "Market Risk Analysts assess and monitor the risk of financial losses arising from changes in market variables such as interest rates, foreign exchange rates, stock prices, commodity prices, and volatility. They help banks, asset managers, hedge funds, and financial institutions manage exposure to market movements.",

  "difficulty": "Hard",

  "goals": [
    "Measure market risk exposure",
    "Prevent excessive trading losses",
    "Protect institutional capital",
    "Support risk-adjusted decision making",
    "Ensure regulatory compliance",
    "Maintain portfolio stability"
  ],

  "bestFor": [
    "People who enjoy financial markets",
    "Analytical thinkers",
    "Individuals comfortable with statistics",
    "People who enjoy working with data",
    "Those interested in risk and trading"
  ],

  "avoidIf": [
    "You dislike numbers and quantitative work",
    "You dislike financial markets",
    "You want client-facing roles",
    "You dislike statistics",
    "You prefer creative careers"
  ],

  "requiredSkills": [
    "Statistics",
    "Financial Markets",
    "Excel",
    "Risk Modelling",
    "Data Analysis",
    "Probability",
    "Fixed Income",
    "Derivatives Knowledge"
  ],

  "collegeImportance": [
    "Moderate to High",
    "Strong quantitative backgrounds are valued",
    "Top institutions help with entry into global banks",
    "Technical skills eventually matter more than pedigree"
  ],

  "familyAdvantage": [
    "Finance industry exposure",
    "Banking connections",
    "Capital markets knowledge",
    "Professional network"
  ],

  "qualifications": [
    "Finance, Economics, Mathematics, Statistics, Engineering Degree",
    "FRM (highly valued)",
    "CFA (valuable)",
    "MBA Finance (optional)",
    "Quantitative Certifications"
  ],

  "realityCheck": [
    "Most of the job involves monitoring risk rather than taking risk",
    "Market Risk is often viewed as the 'guardian' of trading desks",
    "You work closely with traders but are not a trader",
    "Senior management pays close attention to risk reports during market crises",
    "Errors can lead to massive financial losses",
    "The role becomes increasingly strategic at senior levels"
  ],

  "careerGrowth": [
    "Market Risk Analyst",
    "Senior Market Risk Analyst",
    "Risk Manager",
    "Senior Risk Manager",
    "Head of Market Risk",
    "Chief Risk Officer (CRO)"
  ],

  "salary": {
    "entry": "₹8-15 LPA",
    "mid": "₹15-35 LPA",
    "senior": "₹40 LPA - ₹1 Cr+"
  },

  "dayToDayWork": [
    "Monitoring trading positions",
    "Calculating Value at Risk (VaR)",
    "Stress testing portfolios",
    "Analyzing market movements",
    "Preparing risk reports",
    "Working with traders and portfolio managers",
    "Reviewing risk limits",
    "Presenting risk exposures to management"
  ],

  "challenges": [
    "Highly volatile markets",
    "Complex financial instruments",
    "Regulatory requirements",
    "Handling market crises",
    "Managing large datasets",
    "Balancing profitability and risk"
  ],

  "roadmap": [
    "Learn financial markets",
    "Study statistics and probability",
    "Master Excel and data analysis",
    "Understand derivatives and fixed income products",
    "Pursue FRM or CFA",
    "Gain experience in risk, treasury, or capital markets"
  ],

  "exitOpportunities": [
    "Treasury",
    "Asset Management",
    "Trading Support",
    "Quantitative Risk",
    "Portfolio Risk",
    "Investment Risk",
    "Chief Risk Officer Track"
  ],

  "futureOutlook": [
    "Financial institutions continue expanding risk teams",
    "Market complexity increases demand for risk specialists",
    "AI will improve monitoring but not replace judgment",
    "Strong demand in global banking hubs",
    "Excellent long-term stability"
  ],

  "recommendedResource": [
    "FRM Curriculum",
    "John Hull - Risk Management and Financial Institutions",
    "CFA Curriculum",
    "Options, Futures and Other Derivatives",
    "Bloomberg Market Concepts"
  ]
},
{
  "name": "Market Risk Analyst",

  "summary": "Market Risk Analysts assess and monitor the risk of financial losses arising from changes in market variables such as interest rates, foreign exchange rates, stock prices, commodity prices, and volatility. They help banks, asset managers, hedge funds, and financial institutions manage exposure to market movements.",

  "difficulty": "Hard",

  "goals": [
    "Measure market risk exposure",
    "Prevent excessive trading losses",
    "Protect institutional capital",
    "Support risk-adjusted decision making",
    "Ensure regulatory compliance",
    "Maintain portfolio stability"
  ],

  "bestFor": [
    "People who enjoy financial markets",
    "Analytical thinkers",
    "Individuals comfortable with statistics",
    "People who enjoy working with data",
    "Those interested in risk and trading"
  ],

  "avoidIf": [
    "You dislike numbers and quantitative work",
    "You dislike financial markets",
    "You want client-facing roles",
    "You dislike statistics",
    "You prefer creative careers"
  ],

  "requiredSkills": [
    "Statistics",
    "Financial Markets",
    "Excel",
    "Risk Modelling",
    "Data Analysis",
    "Probability",
    "Fixed Income",
    "Derivatives Knowledge"
  ],

  "collegeImportance": [
    "Moderate to High",
    "Strong quantitative backgrounds are valued",
    "Top institutions help with entry into global banks",
    "Technical skills eventually matter more than pedigree"
  ],

  "familyAdvantage": [
    "Finance industry exposure",
    "Banking connections",
    "Capital markets knowledge",
    "Professional network"
  ],

  "qualifications": [
    "Finance, Economics, Mathematics, Statistics, Engineering Degree",
    "FRM (highly valued)",
    "CFA (valuable)",
    "MBA Finance (optional)",
    "Quantitative Certifications"
  ],

  "realityCheck": [
    "Most of the job involves monitoring risk rather than taking risk",
    "Market Risk is often viewed as the 'guardian' of trading desks",
    "You work closely with traders but are not a trader",
    "Senior management pays close attention to risk reports during market crises",
    "Errors can lead to massive financial losses",
    "The role becomes increasingly strategic at senior levels"
  ],

  "careerGrowth": [
    "Market Risk Analyst",
    "Senior Market Risk Analyst",
    "Risk Manager",
    "Senior Risk Manager",
    "Head of Market Risk",
    "Chief Risk Officer (CRO)"
  ],

  "salary": {
    "entry": "₹8-15 LPA",
    "mid": "₹15-35 LPA",
    "senior": "₹40 LPA - ₹1 Cr+"
  },

  "dayToDayWork": [
    "Monitoring trading positions",
    "Calculating Value at Risk (VaR)",
    "Stress testing portfolios",
    "Analyzing market movements",
    "Preparing risk reports",
    "Working with traders and portfolio managers",
    "Reviewing risk limits",
    "Presenting risk exposures to management"
  ],

  "challenges": [
    "Highly volatile markets",
    "Complex financial instruments",
    "Regulatory requirements",
    "Handling market crises",
    "Managing large datasets",
    "Balancing profitability and risk"
  ],

  "roadmap": [
    "Learn financial markets",
    "Study statistics and probability",
    "Master Excel and data analysis",
    "Understand derivatives and fixed income products",
    "Pursue FRM or CFA",
    "Gain experience in risk, treasury, or capital markets"
  ],

  "exitOpportunities": [
    "Treasury",
    "Asset Management",
    "Trading Support",
    "Quantitative Risk",
    "Portfolio Risk",
    "Investment Risk",
    "Chief Risk Officer Track"
  ],

  "futureOutlook": [
    "Financial institutions continue expanding risk teams",
    "Market complexity increases demand for risk specialists",
    "AI will improve monitoring but not replace judgment",
    "Strong demand in global banking hubs",
    "Excellent long-term stability"
  ],

  "recommendedResource": [
    "FRM Curriculum",
    "John Hull - Risk Management and Financial Institutions",
    "CFA Curriculum",
    "Options, Futures and Other Derivatives",
    "Bloomberg Market Concepts"
  ]
},
{
  "name": "Internal Auditor",

  "summary": "Internal Auditors evaluate an organization's financial, operational, compliance, and risk management processes. Their role is to identify weaknesses, improve controls, reduce risks, and ensure that business operations are functioning effectively and ethically.",

  "difficulty": "Medium-Hard",

  "goals": [
    "Identify operational and financial risks",
    "Improve internal controls",
    "Ensure regulatory compliance",
    "Prevent fraud and errors",
    "Improve business processes",
    "Protect organizational assets"
  ],

  "bestFor": [
    "Detail-oriented individuals",
    "Analytical thinkers",
    "People interested in business processes",
    "Professionals who enjoy investigations",
    "Those who like structured work"
  ],

  "avoidIf": [
    "You dislike documentation",
    "You prefer highly creative work",
    "You dislike regulations and compliance",
    "You want aggressive revenue-generating roles",
    "You dislike reviewing processes"
  ],

  "requiredSkills": [
    "Auditing",
    "Risk Assessment",
    "Accounting",
    "Business Process Analysis",
    "Excel",
    "Report Writing",
    "Internal Controls",
    "Communication"
  ],

  "collegeImportance": [
    "Moderate",
    "Accounting and finance backgrounds help",
    "Professional qualifications often matter more later",
    "Performance and technical knowledge drive career progression"
  ],

  "familyAdvantage": [
    "CA background in family",
    "Audit firm exposure",
    "Corporate network",
    "Business ownership exposure"
  ],

  "qualifications": [
    "B.Com, Finance, Accounting, Economics, Engineering",
    "CA (highly valued)",
    "CIA (Certified Internal Auditor)",
    "CPA (optional)",
    "MBA Finance (optional)"
  ],

  "realityCheck": [
    "Internal Auditors are not police officers, despite how employees often view them",
    "Much of the job involves understanding business operations rather than just checking numbers",
    "You often uncover problems that management may not want to hear",
    "The role provides exposure to multiple departments across a company",
    "Senior auditors often interact directly with executives and audit committees",
    "Travel can be significant in large organizations"
  ],

  "careerGrowth": [
    "Audit Associate",
    "Internal Auditor",
    "Senior Internal Auditor",
    "Audit Manager",
    "Senior Audit Manager",
    "Head of Internal Audit",
    "Chief Audit Executive (CAE)",
    "Chief Risk Officer (CRO)"
  ],

  "salary": {
    "entry": "₹5-10 LPA",
    "mid": "₹12-30 LPA",
    "senior": "₹35 LPA - ₹1 Cr+"
  },

  "dayToDayWork": [
    "Reviewing business processes",
    "Testing internal controls",
    "Conducting audits",
    "Interviewing employees",
    "Identifying operational risks",
    "Preparing audit reports",
    "Following up on audit findings",
    "Presenting recommendations to management"
  ],

  "challenges": [
    "Resistance from business teams",
    "Managing tight deadlines",
    "Balancing independence with business relationships",
    "Investigating complex processes",
    "Keeping up with regulations",
    "Identifying hidden risks"
  ],

  "roadmap": [
    "Learn accounting and finance fundamentals",
    "Understand business processes",
    "Gain audit or accounting experience",
    "Develop risk assessment skills",
    "Pursue CA or CIA qualifications",
    "Build expertise in internal controls and governance"
  ],

  "exitOpportunities": [
    "Risk Management",
    "Compliance",
    "Corporate Finance",
    "Operational Excellence",
    "Consulting",
    "Governance",
    "Chief Risk Officer Track",
    "Chief Financial Officer Track"
  ],

  "futureOutlook": [
    "Increasing regulations support demand",
    "Companies are strengthening governance frameworks",
    "Cybersecurity and operational audits are growing areas",
    "AI will automate routine testing but not professional judgment",
    "Strong long-term stability"
  ],

  "recommendedResource": [
    "Institute of Internal Auditors (IIA)",
    "CIA Curriculum",
    "COSO Internal Control Framework",
    "The Internal Auditing Handbook",
    "Risk Management and Internal Control Resources"
  ]
},
{
  "name": "AML / KYC Analyst",

  "summary": "AML (Anti-Money Laundering) and KYC (Know Your Customer) Analysts help financial institutions prevent financial crimes by verifying customer identities, monitoring transactions, investigating suspicious activities, and ensuring compliance with regulatory requirements.",

  "difficulty": "Medium",

  "goals": [
    "Prevent money laundering",
    "Detect suspicious transactions",
    "Ensure regulatory compliance",
    "Protect financial institutions from financial crime",
    "Reduce fraud risks",
    "Support financial system integrity"
  ],

  "bestFor": [
    "Detail-oriented individuals",
    "People interested in financial crime investigations",
    "Analytical thinkers",
    "Professionals who enjoy compliance work",
    "People who can follow procedures carefully"
  ],

  "avoidIf": [
    "You dislike repetitive work",
    "You want highly strategic roles",
    "You dislike documentation",
    "You want revenue-generating careers",
    "You dislike regulations"
  ],

  "requiredSkills": [
    "Attention to Detail",
    "Financial Crime Awareness",
    "Risk Assessment",
    "Investigation Skills",
    "Compliance Knowledge",
    "Report Writing",
    "Data Analysis",
    "Regulatory Understanding"
  ],

  "collegeImportance": [
    "Low to Moderate",
    "Finance, commerce, law, and business backgrounds are common",
    "Certifications and experience become more important over time",
    "The field is relatively accessible compared to investment banking or consulting"
  ],

  "familyAdvantage": [
    "Minimal advantage",
    "Banking exposure can help",
    "Professional networks may help secure interviews",
    "Performance matters significantly more than connections"
  ],

  "qualifications": [
    "Bachelor's Degree",
    "Finance, Commerce, Law, Economics, Business Administration",
    "Tier 2 and Tier 3 colleges are well represented",
    "CAMS (Certified Anti-Money Laundering Specialist)",
    "ICA Certifications",
    "Compliance Certifications"
  ],

  "realityCheck": [
    "The work can be repetitive at junior levels",
    "Accuracy is more important than speed",
    "You are often reviewing large volumes of customer information",
    "Mistakes can expose institutions to regulatory penalties",
    "The job becomes more investigative and strategic at senior levels",
    "Many professionals use AML/KYC as an entry point into broader compliance and risk careers"
  ],

  "careerGrowth": [
    "KYC Analyst",
    "AML Analyst",
    "Senior AML Analyst",
    "AML Investigator",
    "Compliance Manager",
    "Head of Financial Crime Compliance",
    "Chief Compliance Officer (CCO)"
  ],

  "salary": {
    "entry": "₹3-7 LPA",
    "mid": "₹8-18 LPA",
    "senior": "₹20 LPA - ₹60 LPA+"
  },

  "dayToDayWork": [
    "Verifying customer identities",
    "Reviewing account opening documents",
    "Conducting due diligence checks",
    "Monitoring suspicious transactions",
    "Investigating unusual activity",
    "Preparing compliance reports",
    "Screening sanctions lists",
    "Escalating suspicious cases"
  ],

  "challenges": [
    "Large transaction volumes",
    "Changing regulations",
    "False positive alerts",
    "Maintaining accuracy",
    "Investigating complex financial activities",
    "Regulatory scrutiny"
  ],

  "roadmap": [
    "Learn banking and financial services basics",
    "Understand AML and KYC regulations",
    "Develop investigation and analytical skills",
    "Gain experience in banking operations or compliance",
    "Pursue CAMS certification",
    "Move into AML investigations or compliance leadership"
  ],

  "exitOpportunities": [
    "Compliance",
    "Risk Management",
    "Fraud Investigation",
    "Financial Crime Consulting",
    "Regulatory Compliance",
    "Internal Audit",
    "Corporate Governance"
  ],

  "futureOutlook": [
    "Financial crime regulations continue to increase globally",
    "Banks and fintech companies are expanding compliance teams",
    "AI will automate basic screening but not investigations",
    "Strong demand in banking, fintech, and payments industries",
    "Stable long-term career path"
  ],

  "recommendedResource": [
    "ACAMS Resources",
    "CAMS Certification",
    "FATF Guidelines",
    "ICA Certifications",
    "AML RightSource Learning Materials"
  ]
}
    ]

}